logging_handler/__init__.py
logging_handler-1.0.7.dist-info/LICENSE
logging_handler-1.0.7.dist-info/METADATA
logging_handler-1.0.7.dist-info/WHEEL
logging_handler-1.0.7.dist-info/top_level.txt
logging_handler-1.0.7.dist-info/RECORD
