Metadata-Version: 2.1
Name: logging_handler
Version: 1.0.7
Summary: Python Library to quickly create logging handlers
Author-email: Thomas Dunteman <git@learningtopi.com>
Project-URL: Homepage, https://www.learningtopi.com/python-modules-applications/python_logging_handler/
Project-URL: Bug Tracker, https://github.com/LearningToPi/logging_handler/issues
Project-URL: Source Code, https://github.com/LearningToPi/logging_handler
Keywords: logging,syslog
Classifier: Topic :: System :: Logging
Classifier: License :: OSI Approved :: MIT License
Classifier: Operating System :: OS Independent
Classifier: Programming Language :: Python :: 3
Requires-Python: >=3.6
License-File: LICENSE
